jsonresolver/__init__.py
jsonresolver/core.py
jsonresolver/decorators.py
jsonresolver/hookimpl.py
jsonresolver/hookspec.py
jsonresolver/contrib/__init__.py
jsonresolver/contrib/jsonref.py
jsonresolver/contrib/jsonschema.py
jsonresolver-0.4.1.dist-info/licenses/AUTHORS.rst
jsonresolver-0.4.1.dist-info/licenses/LICENSE
jsonresolver-0.4.1.dist-info/METADATA
jsonresolver-0.4.1.dist-info/WHEEL
jsonresolver-0.4.1.dist-info/top_level.txt
jsonresolver-0.4.1.dist-info/RECORD
