Metadata-Version: 2.4
Name: jsonresolver
Version: 0.4.1
Summary: JSON data resolver with support for plugins.
Home-page: https://github.com/inveniosoftware/jsonresolver
Author: Invenio collaboration
Author-email: info@inveniosoftware.org
License: BSD
Platform: any
Classifier: Development Status :: 5 - Production/Stable
Requires-Python: >=3.7
License-File: LICENSE
License-File: AUTHORS.rst
Requires-Dist: pluggy<2,>=1.0
Requires-Dist: werkzeug>=1.0.0
Provides-Extra: tests
Requires-Dist: pytest-black>=0.3.0; extra == "tests"
Requires-Dist: mock>=1.3.0; extra == "tests"
Requires-Dist: pytest-cache>=1.0; extra == "tests"
Requires-Dist: requests>=2.7.0; extra == "tests"
Requires-Dist: pytest-invenio<4.0.0,>=3.0.0; extra == "tests"
Requires-Dist: sphinx>=4.5; extra == "tests"
Requires-Dist: jsonref>=1.0.0; extra == "tests"
Requires-Dist: jsonschema>=2.5.1; extra == "tests"
Provides-Extra: docs
Provides-Extra: jsonref
Requires-Dist: jsonref>=1.0.0; extra == "jsonref"
Provides-Extra: jsonschema
Requires-Dist: jsonschema>=2.5.1; extra == "jsonschema"
Dynamic: license-file
